gamarts/__init__.py
gamarts/_common.py
gamarts/art/__init__.py
gamarts/art/art.py
gamarts/art/file.py
gamarts/art/geometry.py
gamarts/mask/__init__.py
gamarts/mask/geometry.py
gamarts/mask/mask.py
gamarts/mask/transformation.py
gamarts/transform/__init__.py
gamarts/transform/combination.py
gamarts/transform/convert.py
gamarts/transform/drawing.py
gamarts/transform/effect.py
gamarts/transform/transformation.py
gamarts-1.1.1.dist-info/LICENSE
gamarts-1.1.1.dist-info/METADATA
gamarts-1.1.1.dist-info/WHEEL
gamarts-1.1.1.dist-info/top_level.txt
gamarts-1.1.1.dist-info/RECORD
