Metadata-Version: 2.2
Name: gamarts
Version: 1.1.1
Summary: Gamarts is a python library providing a unique way to represent static and animated surfaces in pygame, alongside with a clever loading and unloading behavior.
Home-page: https://github.com/Tanguy-ddv/gamarts
Author: Tanguy Dugas du Villard
Classifier: Programming Language :: Python :: 3
Classifier: Operating System :: OS Independent
Classifier: Development Status :: 5 - Production/Stable
Classifier: Intended Audience :: Developers
Classifier: Topic :: Games/Entertainment
Classifier: Topic :: Software Development :: Libraries :: pygame
Requires-Python: >=3.6
License-File: LICENSE
Requires-Dist: pygame
Requires-Dist: pygame-cv
Requires-Dist: ZOCallable
Requires-Dist: pillow
Dynamic: author
Dynamic: classifier
Dynamic: description
Dynamic: description-content-type
Dynamic: home-page
Dynamic: requires-dist
Dynamic: requires-python
Dynamic: summary
